DSD_HW1/DSD_HW1_b10502013/1-ALU/1_assign/alu_assign.v
//RTL (use continuous assignment)
module alu_assign(
    ctrl,
    x,
    y,
    carry,
    out  
);
    
    input  [3:0] ctrl;
    input  [7:0] x;
    input  [7:0] y;
    output       carry;
    output [7:0] out;

    assign {carry, out} = (ctrl == 4'b0000) ? $signed(x) + $signed(y)
                        :  (ctrl == 4'b0001) ? $signed(x) - $signed(y)
                        :  (ctrl == 4'b0010) ? x & y    
                        :  (ctrl == 4'b0011) ? x | y    
                        :  (ctrl == 4'b0100) ? ~x       
                        :  (ctrl == 4'b0101) ? x^y      
                        :  (ctrl == 4'b0110) ? ~(x|y)   
                        :  (ctrl == 4'b0111) ? y<<x[2:0]
                        :  (ctrl == 4'b1000) ? y>>x[2:0]
                        :  (ctrl == 4'b1001) ? {x[7],x[7:1]}
                        :  (ctrl == 4'b1010) ? {x[6:0] , x[7]} 
                        :  (ctrl == 4'b1011) ? {x[0] , x[7:1]}
                        :  (ctrl == 4'b1100) ? ((x==y)?9'd1:9'd0)
                        :  0;

endmodule

DSD_HW1/DSD_HW1_b10502013/1-ALU/1_assign/alu_assign_tb2.v
`timescale 1ns / 1ps

module alu_assign_tb;

    // Parameters
    parameter CLK_PERIOD = 10; // Clock period in ns

    // Inputs
    reg [3:0] ctrl;
    reg [7:0] x;
    reg [7:0] y;
    reg [8:0] ans;
    reg [3:0] count;

    // Outputs
    wire carry;
    wire [7:0] out;

    // Instantiate the unit under test (UUT)
    alu_assign dut (
        .ctrl(ctrl),
        .x(x),
        .y(y),
        .carry(carry),
        .out(out)
    );

    // Clock generation
    reg clk = 0;
    always #((CLK_PERIOD)/2) clk = ~clk;

    initial begin
        $dumpfile("alu_assign.vcd"); // Set the VCD dumpfile
        $dumpvars; // Dump all variables
    end

    // Test cases
    initial begin
        // Test case 1: Addition
        ctrl = 4'b0000;
        x = 8'b1111_1111; 
        y = 8'b0000_0001; // 5
        ans = 9'b1_0000_0000;
        count = 1;
        #10;
        if ({carry, out} == ans) $display("Test case %d passed", count);
        else $display("Test case %d failed, ans = %b, carry = %b, out = %b",count, ans, carry, out);

        // Test case 2: Subtraction
        ctrl = 4'b0001;
        x = 8'h05; // 5
        y = 8'h0A; // 10
        ans = 9'b1_1111_1011;
        count = 2;
        #10;
        if ({carry, out} == ans) $display("Test case %d passed", count);
        else $display("Test case %d failed, ans = %b, carry = %b, out = %b",count, ans, carry, out);

        // Test case 3: Bitwise AND
        ctrl = 4'b0010;
        x = 8'h0A; // 10
        y = 8'h05; // 5
        ans = 9'b0_0000_0000;
        count = 3;
        #10;
        if ({carry, out} == ans) $display("Test case %d passed", count);
        else $display("Test case %d failed, ans = %b, carry = %b, out = %b",count, ans, carry, out);

        // Test case 4: Bitwise OR
        ctrl = 4'b0011;
        x = 8'h0A; // 10
        y = 8'h05; // 5
        ans = 9'b0_0000_1111;
        count = 4;
        #10;
        if ({carry, out} == ans) $display("Test case %d passed", count);
        else $display("Test case %d failed, ans = %b, carry = %b, out = %b",count, ans, carry, out);

        // Test case 5: Bitwise OR
        ctrl = 4'b0100;
        x = 8'd10; // 10
        y = 8'h05; // 5
        ans = 9'b1_1111_0101;
        count = 5;
        #10;
        if ({carry, out} == ans) $display("Test case %d passed", count);
        else $display("Test case %d failed, ans = %b, carry = %b, out = %b",count, ans, carry, out);

        // Test case 6:
        ctrl = 4'b0101;
        x = 8'h0A; // 10
        y = 8'h05; // 5
        ans = 9'b0_0000_1111;
        count = 6;
        #10;
        if ({carry, out} == ans) $display("Test case %d passed", count);
        else $display("Test case %d failed, ans = %b, carry = %b, out = %b",count, ans, carry, out);

        // Test case 7:
        ctrl = 4'b0110;
        x = 8'h0A; // 10
        y = 8'h05; // 5
        ans = 9'b1_1111_0000;
        count = 7;
        #10;
        if ({carry, out} == ans) $display("Test case %d passed", count);
        else $display("Test case %d failed, ans = %b, carry = %b, out = %b",count, ans, carry, out);

        ctrl = 4'b0111;
        x = 8'h0A; // 10
        y = 8'h05; // 5
        ans = 9'b0_0001_0100;
        count = 8;
        #10;
        if ({carry, out} == ans) $display("Test case %d passed", count);
        else $display("Test case %d failed, ans = %b, carry = %b, out = %b",count, ans, carry, out);

        ctrl = 4'b1000;
        x = 8'h0A; // 10
        y = 8'h05; // 5
        ans = 9'b0_0000_0001;
        count = 9;
        #10;
        if ({carry, out} == ans) $display("Test case %d passed", count);
        else $display("Test case %d failed, ans = %b, carry = %b, out = %b",count, ans, carry, out);

        ctrl = 4'b1001;
        x = 8'h0A; // 10
        y = 8'h05; // 5
        ans = 9'b0_0000_0101;
        count = 10;
        #10;
        if ({carry, out} == ans) $display("Test case %d passed", count);
        else $display("Test case %d failed, ans = %b, carry = %b, out = %b",count, ans, carry, out);

        ctrl = 4'b1010;
        x = 8'h0A; // 10
        y = 8'h05; // 5
        ans = 9'b0_0001_0100;
        count = 11;
        #10;
        if ({carry, out} == ans) $display("Test case %d passed", count);
        else $display("Test case %d failed, ans = %b, carry = %b, out = %b",count, ans, carry, out);
        
        ctrl = 4'b1010;
        x = 8'h0A; // 10
        y = 8'h05; // 5
        ans = 9'b0_0001_0100;
        count = 12;
        #10;
        if ({carry, out} == ans) $display("Test case %d passed", count);
        else $display("Test case %d failed, ans = %b, carry = %b, out = %b",count, ans, carry, out);

        ctrl = 4'b1100;
        x = 8'h0A; // 10
        y = 8'h05; // 5
        ans = 0;
        count = 13;
        #10;
        if ({carry, out} == ans) $display("Test case %d passed", count);
        else $display("Test case %d failed, ans = %b, carry = %b, out = %b",count, ans, carry, out);

        $finish;
    end

endmodule

DSD_HW1/DSD_HW1_b10502013/1-ALU/1_assign/alu_assign.vcd
$date
	Wed Mar 27 21:22:23 2024
$end
$version
	Icarus Verilog
$end
$timescale
	1ps
$end
$scope module alu_assign_tb $end
$var wire 8 ! out [7:0] $end
$var wire 1 " carry $end
$var parameter 32 # CLK_PERIOD $end
$var reg 9 $ ans [8:0] $end
$var reg 1 % clk $end
$var reg 4 & count [3:0] $end
$var reg 4 ' ctrl [3:0] $end
$var reg 8 ( x [7:0] $end
$var reg 8 ) y [7:0] $end
$scope module dut $end
$var wire 4 * ctrl [3:0] $end
$var wire 8 + x [7:0] $end
$var wire 8 , y [7:0] $end
$var wire 8 - out [7:0] $end
$var wire 1 " carry $end
$upscope $end
$upscope $end
$enddefinitions $end
$comment Show the parameter values. $end
$dumpall
b1010 #
$end
#0
$dumpvars
b0 -
b1 ,
b11111111 +
b0 *
b1 )
b11111111 (
b0 '
b1 &
0%
b100000000 $
1"
b0 !
$end
#5000
1%
#10000
b11111011 !
b11111011 -
0%
b10 &
b111111011 $
b1010 )
b1010 ,
b101 (
b101 +
b1 '
b1 *
#15000
1%
#20000
b0 !
b0 -
0"
0%
b11 &
b0 $
b101 )
b101 ,
b1010 (
b1010 +
b10 '
b10 *
#25000
1%
#30000
b1111 !
b1111 -
0%
b100 &
b1111 $
b11 '
b11 *
#35000
1%
#40000
b11110101 !
b11110101 -
1"
0%
b101 &
b111110101 $
b100 '
b100 *
#45000
1%
#50000
b1111 !
b1111 -
0"
0%
b110 &
b1111 $
b101 '
b101 *
#55000
1%
#60000
b11110000 !
b11110000 -
1"
0%
b111 &
b111110000 $
b110 '
b110 *
#65000
1%
#70000
b10100 !
b10100 -
0"
0%
b1000 &
b10100 $
b111 '
b111 *
#75000
1%
#80000
b1 !
b1 -
0%
b1001 &
b1 $
b1000 '
b1000 *
#85000
1%
#90000
b101 !
b101 -
0%
b1010 &
b101 $
b1001 '
b1001 *
#95000
1%
#100000
b10100 !
b10100 -
0%
b1011 &
b10100 $
b1010 '
b1010 *
#105000
1%
#110000
0%
b1100 &
#115000
1%
#120000
b0 !
b0 -
0%
b1101 &
b0 $
b1100 '
b1100 *
