DSD_HW1/3-SimpleCalculator/simple_calculator.v
module simple_calculator(
    Clk,
    WEN,
    RW,
    RX,
    RY,
    DataIn,
    Sel,
    Ctrl,
    busY,
    Carry
);

    input        Clk;
    input        WEN;
    input  [2:0] RW, RX, RY;
    input  [7:0] DataIn;
    input        Sel;
    input  [3:0] Ctrl;
    output [7:0] busY;
    output       Carry;

// declaration of wire/reg
    reg [7:0] r0_w, r1_w, r2_w, r3_w, r4_w, r5_w, r6_w, r7_w;
    reg [7:0] r0_r, r1_r, r2_r, r3_r, r4_r, r5_r, r6_r, r7_r;
    reg [7:0] X, Y;       
    reg carry;
    reg [7:0] invert;

//Initialize
    initial begin
        r0_r = 8'h00; 
        r1_r = 8'h00; 
        r2_r = 8'h00;
        r3_r = 8'h00;
        r4_r = 8'h00;
        r5_r = 8'h00;
        r6_r = 8'h00;
        r7_r = 8'h00;
    end

// submodule instantiation

    assign Carry = carry;
    assign busY  = Y;

    always@(*) begin
        //initial
        r0_w = r0_r;
        r1_w = r1_r;
        r2_w = r2_r;
        r3_w = r3_r;
        r4_w = r4_r;
        r5_w = r5_r;
        r6_w = r6_r;
        r7_w = r7_r;

        //8x8 Register
        case (RY)
            3'b000 : Y = r0_r;
            3'b001 : Y = r1_r;
            3'b010 : Y = r2_r;
            3'b011 : Y = r3_r;
            3'b100 : Y = r4_r;
            3'b101 : Y = r5_r;
            3'b110 : Y = r6_r;
            3'b111 : Y = r7_r; 
        endcase

        //MUX
        if (Sel) begin
            case (RX)
                3'b000 : X = r0_r;
                3'b001 : X = r1_r;
                3'b010 : X = r2_r;
                3'b011 : X = r3_r;
                3'b100 : X = r4_r;
                3'b101 : X = r5_r;
                3'b110 : X = r6_r;
                3'b111 : X = r7_r; 
            endcase    
        end
        else begin
            X = DataIn;
        end
    end

    //ALU
    always @(*) begin
        case (Ctrl)
            4'b0000 : {carry, invert} = X + Y;
            4'b0001 : {carry, invert} = $signed(X - Y);
            4'b0010 : {carry, invert} = X & Y;
            4'b0011 : {carry, invert} = X | Y;
            4'b0100 : {carry, invert} = ~X;
            4'b0101 : {carry, invert} = X ^ Y;
            4'b0110 : {carry, invert} = ~(X | Y);
            4'b0111 : {carry, invert} = Y << X[2:0];
            4'b1000 : {carry, invert} = Y >> X[2:0];
            4'b1001 : {carry, invert} = {X[7], X[7:1]};
            4'b1010 : {carry, invert} = {X[6:0], X[7]};
            4'b1011 : {carry, invert} = {X[0], X[7:1]};
            4'b1100 : {carry, invert} = ((X == Y) ? 1:0);
            default : {carry, invert} = 0;
        endcase
    end
    
    //Sequential
    always@(posedge Clk) begin
        if (WEN) begin
            case (RW)
                3'b000 : r0_r <= invert;
                3'b001 : r1_r <= invert;
                3'b010 : r2_r <= invert;
                3'b011 : r3_r <= invert;
                3'b100 : r4_r <= invert;
                3'b101 : r5_r <= invert;
                3'b110 : r6_r <= invert;
                3'b111 : r7_r <= invert;
            endcase
        end
        else begin
            r0_r <= r0_w;
            r1_r <= r1_w;
            r2_r <= r2_w;
            r3_r <= r3_w;
            r4_r <= r4_w;
            r5_r <= r5_w;
            r6_r <= r6_w;
            r7_r <= r7_w;
        end
    end	

endmodule

DSD_HW1/DSD_HW1_b10502013/3-SimpleCalculator/simple_calculator_tb.v
`timescale 1ns/10ps
`define CYCLE  10
`define HCYCLE  5

module simple_calculator_tb;
    // port declaration for design-under-test
    reg        Clk;
    reg        WEN;
    reg  [2:0] RW, RX, RY;
    reg  [7:0] DataIn;
    reg        Sel;
    reg  [3:0] Ctrl;
    wire [7:0] busY;
    wire       Carry;
 
    // instantiate the design-under-test
    simple_calculator u_calc(
        .Clk    (Clk),
        .WEN    (WEN),
        .RW     (RW),
        .RX     (RX),
        .RY     (RY),
        .DataIn (DataIn),
        .Sel    (Sel),
        .Ctrl   (Ctrl),
        .busY   (busY),
        .Carry  (Carry)
    );

    // waveform dump
    // initial begin
    //    $fsdbDumpfile("simple_calc.fsdb");
    //    $fsdbDumpvars;
    // end
    initial begin
        $dumpfile("simple_calculator.vcd"); // Set the VCD dumpfile
        $dumpvars; // Dump all variables
    end
    
    // clock generation
    always#(`HCYCLE) Clk = ~Clk;
    
    // test pattern
    parameter A = {4'd0,4'd13};
    parameter B = {4'd0,4'd12};
    parameter maskB0 = {8{B[0]}};
    parameter maskB1 = {8{B[1]}};
    parameter maskB2 = {8{B[2]}};
    parameter maskB3 = {8{B[3]}};
    parameter sum0 = A*B[0];
    parameter sum1 = A*B[1:0];
    parameter sum2 = A*B[2:0];
    parameter C = A*B;
    
    // simulation
    integer err_count;
    initial begin
        // initialization
        Clk = 1'b1;
        err_count = 0;
        
        // 4-bit x 4-bit unsigned multiplication
        $display( "4-bit x 4-bit unsigned multiplication" );
        
        #(`CYCLE*0.2)
        $display( "1: store multiplicand A=%2d in REG#1", A );
        $display( "    [REG#1 = add %b REG#0]", A );        
        WEN = 1'b1; RW = 3'd1; RX = 3'd0; RY = 3'd0;
        Ctrl = 4'b0000; Sel = 1'b0; DataIn = A;
        #(`CYCLE*0.8)
        #(`CYCLE*0.2)
        WEN = 1'b0; RW = 3'd1; RX = 3'd0; RY = 3'd1;
        Ctrl = 4'b0011; Sel = 1'b0; DataIn = 8'd0;
        #(`CYCLE*0.3)
        if( busY==A ) $display( "    .... passed." );
        else begin 
            err_count = err_count+1;
            $display( "    .... failed, design(%b) != expected(%b)", busY, A );
        end
        #(`HCYCLE)
        
        #(`CYCLE*0.2)
        $display( "2: store multiplier B=%2d in REG#2", B );
        $display( "    [REG#2 = add %b REG#0]", B ); 
        WEN = 1'b1; RW = 3'd2; RX = 3'd0; RY = 3'd0;
        Ctrl = 4'b0000; Sel = 1'b0; DataIn = B;
        #(`CYCLE*0.8)
        #(`CYCLE*0.2)
        WEN = 1'b0; RW = 3'd1; RX = 3'd0; RY = 3'd2;
        Ctrl = 4'b0011; Sel = 1'b0; DataIn = 8'd0;
        #(`CYCLE*0.3)
        if( busY==B ) $display( "    .... passed." );
        else begin 
            err_count = err_count+1;
            $display( "    .... failed, design(%b) != expected(%b)", busY, B );
        end
        #(`HCYCLE)        
        
        #(`CYCLE*0.2)
        $display( "3: set REG#3 = (B[0]==1)? 8'b11111111: 8'b00000000" );
        $display( "    [REG#3 = and 0000_0001 REG#2]" ); 
        WEN = 1'b1; RW = 3'd3; RX = 3'd0; RY = 3'd2;
        Ctrl = 4'b0010; Sel = 1'b0; DataIn = 8'd1;
        #(`CYCLE*0.8)
        #(`CYCLE*0.2)
        $display( "    [REG#3 = sub REG#0 REG#3]" ); 
        WEN = 1'b1; RW = 3'd3; RX = 3'd0; RY = 3'd3;
        Ctrl = 4'b0001; Sel = 1'b1; DataIn = 8'd0;
        #(`CYCLE*0.8)
        #(`CYCLE*0.2)
        WEN = 1'b0; RW = 3'd3; RX = 3'd0; RY = 3'd3;
        Ctrl = 4'b0011; Sel = 1'b1; DataIn = 8'd0;
        #(`CYCLE*0.3)
        if( busY==maskB0 ) $display( "    .... passed." );
        else begin
            err_count = err_count+1;
            $display( "    .... failed, design(%b) != expected(%b)", busY, maskB0 );
        end
        #(`HCYCLE)         

        #(`CYCLE*0.2)
        $display( "4: set REG#4 = (B[1]==1)? 8'b11111111: 8'b00000000" );
        $display( "    [REG#2 = sra REG#2]" ); 
        WEN = 1'b1; RW = 3'd2; RX = 3'd2; RY = 3'd2;
        Ctrl = 4'b1001; Sel = 1'b1; DataIn = 8'd0;
        #(`CYCLE*0.8)
        #(`CYCLE*0.2)
        $display( "    [REG#4 = and 0000_0001 REG#2]" ); 
        WEN = 1'b1; RW = 3'd4; RX = 3'd0; RY = 3'd2;
        Ctrl = 4'b0010; Sel = 1'b0; DataIn = 8'd1;
        #(`CYCLE*0.8)
        #(`CYCLE*0.2)
        $display( "    [REG#4 = sub REG#0 REG#4]" ); 
        WEN = 1'b1; RW = 3'd4; RX = 3'd0; RY = 3'd4;
        Ctrl = 4'b0001; Sel = 1'b1; DataIn = 8'd0;
        #(`CYCLE*0.8)
        #(`CYCLE*0.2)
        WEN = 1'b0; RW = 3'd4; RX = 3'd0; RY = 3'd4;
        Ctrl = 4'b0011; Sel = 1'b1; DataIn = 8'd0;
        #(`CYCLE*0.3)
        if( busY==maskB1 ) $display( "    .... passed." );
        else begin 
            err_count = err_count+1;
            $display( "    .... failed, design(%b) != expected(%b)", busY, maskB1 );
        end
        #(`HCYCLE)  

        #(`CYCLE*0.2)
        $display( "5: set REG#5 = (B[2]==1)? 8'b11111111: 8'b00000000" );
        $display( "    [REG#2 = sra REG#2]" ); 
        WEN = 1'b1; RW = 3'd2; RX = 3'd2; RY = 3'd2;
        Ctrl = 4'b1001; Sel = 1'b1; DataIn = 8'd0;
        #(`CYCLE*0.8)
        #(`CYCLE*0.2)
        $display( "    [REG#5 = and 0000_0001 REG#2]" ); 
        WEN = 1'b1; RW = 3'd5; RX = 3'd0; RY = 3'd2;
        Ctrl = 4'b0010; Sel = 1'b0; DataIn = 8'd1;
        #(`CYCLE*0.8)
        #(`CYCLE*0.2)
        $display( "    [REG#5 = sub REG#0 REG#5]" ); 
        WEN = 1'b1; RW = 3'd5; RX = 3'd0; RY = 3'd5;
        Ctrl = 4'b0001; Sel = 1'b1; DataIn = 8'd0;
        #(`CYCLE*0.8)
        #(`CYCLE*0.2)
        WEN = 1'b0; RW = 3'd5; RX = 3'd0; RY = 3'd5;
        Ctrl = 4'b0011; Sel = 1'b1; DataIn = 8'd0;
        #(`CYCLE*0.3)
        if( busY==maskB2 ) $display( "    .... passed." );
        else begin 
            err_count = err_count+1;
            $display( "    .... failed, design(%b) != expected(%b)", busY, maskB2 );
        end
        #(`HCYCLE) 
    
        #(`CYCLE*0.2)
        $display( "6: set REG#6 = (B[3]==1)? 8'b11111111: 8'b00000000" );
        $display( "    [REG#2 = sra REG#2]" ); 
        WEN = 1'b1; RW = 3'd2; RX = 3'd2; RY = 3'd2;
        Ctrl = 4'b1001; Sel = 1'b1; DataIn = 8'd0;
        #(`CYCLE*0.8)
        #(`CYCLE*0.2)
        $display( "    [REG#6 = and 0000_0001 REG#2]" ); 
        WEN = 1'b1; RW = 3'd6; RX = 3'd0; RY = 3'd2;
        Ctrl = 4'b0010; Sel = 1'b0; DataIn = 8'd1;
        #(`CYCLE*0.8)
        #(`CYCLE*0.2)
        $display( "    [REG#6 = sub REG#0 REG#6]" ); 
        WEN = 1'b1; RW = 3'd6; RX = 3'd0; RY = 3'd6;
        Ctrl = 4'b0001; Sel = 1'b1; DataIn = 8'd0;
        #(`CYCLE*0.8)
        #(`CYCLE*0.2)
        WEN = 1'b0; RW = 3'd6; RX = 3'd0; RY = 3'd6;
        Ctrl = 4'b0011; Sel = 1'b1; DataIn = 8'd0;
        #(`CYCLE*0.3)
        if( busY==maskB3 ) $display( "    .... passed." );
        else begin
            err_count = err_count+1;
            $display( "    .... failed, design(%b) != expected(%b)", busY, maskB3 );
        end
        #(`HCYCLE) 
        
        $display( "7: shift & summation, REG#7 = A*B[0]" );
        #(`CYCLE*0.2)
        $display( "    [REG#3 = and REG#1 REG#3]" ); 
        WEN = 1'b1; RW = 3'd3; RX = 3'd1; RY = 3'd3;
        Ctrl = 4'b0010; Sel = 1'b1; DataIn = 8'd0;
        #(`CYCLE*0.8)
        #(`CYCLE*0.2)
        $display( "    [REG#7 = add REG#0 REG#3]" ); 
        WEN = 1'b1; RW = 3'd7; RX = 3'd0; RY = 3'd3;
        Ctrl = 4'b0000; Sel = 1'b1; DataIn = 8'd0;
        #(`CYCLE*0.8)
        #(`CYCLE*0.2)
        WEN = 1'b0; RW = 3'd7; RX = 3'd0; RY = 3'd7;
        Ctrl = 4'b0011; Sel = 1'b1; DataIn = 8'd0;
        #(`CYCLE*0.3)
        if( busY==sum0 ) $display( "    .... passed." );
        else begin
            err_count = err_count+1;
            $display( "    .... failed, design(%b) != expected(%b)", busY, sum0 );
        end
        #(`HCYCLE)
        
        $display( "8: shift & summation, REG#7 = A*B[1:0]" );
        #(`CYCLE*0.2)
        $display( "    [REG#4 = and REG#1 REG#4]" );
        WEN = 1'b1; RW = 3'd4; RX = 3'd1; RY = 3'd4;
        Ctrl = 4'b0010; Sel = 1'b1; DataIn = 8'd0;
        #(`CYCLE*0.8)
        #(`CYCLE*0.2)
        $display( "    [REG#4 = sll 0000_0001 REG#4]" );
        WEN = 1'b1; RW = 3'd4; RX = 3'd0; RY = 3'd4;
        Ctrl = 4'b0111; Sel = 1'b0; DataIn = 8'd1;
        #(`CYCLE*0.8)
        #(`CYCLE*0.2)
        $display( "    [REG#7 = add REG#7 REG#4]" ); 
        WEN = 1'b1; RW = 3'd7; RX = 3'd7; RY = 3'd4;
        Ctrl = 4'b0000; Sel = 1'b1; DataIn = 8'd0;
        #(`CYCLE*0.8)
        #(`CYCLE*0.2)
        WEN = 1'b0; RW = 3'd7; RX = 3'd0; RY = 3'd7;
        Ctrl = 4'b0011; Sel = 1'b1; DataIn = 8'd0;
        #(`CYCLE*0.3)
        if( busY==sum1 ) $display( "    .... passed." );
        else begin     
            err_count = err_count+1;
            $display( "    .... failed, design(%b) != expected(%b)", busY, sum1 );
        end
        #(`HCYCLE)
        
        $display( "9: shift & summation, REG#7 = A*B[2:0]" );
        #(`CYCLE*0.2)
        $display( "    [REG#5 = and REG#1 REG#5]" );
        WEN = 1'b1; RW = 3'd5; RX = 3'd1; RY = 3'd5;
        Ctrl = 4'b0010; Sel = 1'b1; DataIn = 8'd0;
        #(`CYCLE*0.8)
        #(`CYCLE*0.2)
        $display( "    [REG#5 = sll 0000_0010 REG#5]" );
        WEN = 1'b1; RW = 3'd5; RX = 3'd0; RY = 3'd5;
        Ctrl = 4'b0111; Sel = 1'b0; DataIn = 8'd2;
        #(`CYCLE*0.8)
        #(`CYCLE*0.2)
        $display( "    [REG#7 = add REG#7 REG#5]" ); 
        WEN = 1'b1; RW = 3'd7; RX = 3'd7; RY = 3'd5;
        Ctrl = 4'b0000; Sel = 1'b1; DataIn = 8'd0;
        #(`CYCLE*0.8)
        #(`CYCLE*0.2)
        WEN = 1'b0; RW = 3'd7; RX = 3'd0; RY = 3'd7;
        Ctrl = 4'b0011; Sel = 1'b1; DataIn = 8'd0;
        #(`CYCLE*0.3)
        if( busY==sum2 ) $display( "    .... passed." );
        else begin 
            err_count = err_count+1;
            $display( "    .... failed, design(%b) != expected(%b)", busY, sum2 );
        end
        #(`HCYCLE)
        
        $display( "10:shift & summation, REG#7 = A*B" );
        #(`CYCLE*0.2)
        $display( "    [REG#6 = and REG#1 REG#6]" );
        WEN = 1'b1; RW = 3'd6; RX = 3'd1; RY = 3'd6;
        Ctrl = 4'b0010; Sel = 1'b1; DataIn = 8'd0;
        #(`CYCLE*0.8)
        #(`CYCLE*0.2)
        $display( "    [REG#6 = sll 0000_0011 REG#6]" );
        WEN = 1'b1; RW = 3'd6; RX = 3'd0; RY = 3'd6;
        Ctrl = 4'b0111; Sel = 1'b0; DataIn = 8'd3;
        #(`CYCLE*0.8)
        #(`CYCLE*0.2)
        $display( "    [REG#7 = add REG#7 REG#6]" ); 
        WEN = 1'b1; RW = 3'd7; RX = 3'd7; RY = 3'd6;
        Ctrl = 4'b0000; Sel = 1'b1; DataIn = 8'd0;
        #(`CYCLE*0.8)
        #(`CYCLE*0.2)
        WEN = 1'b0; RW = 3'd7; RX = 3'd0; RY = 3'd7;
        Ctrl = 4'b0011; Sel = 1'b1; DataIn = 8'd0;
        #(`CYCLE*0.3)
        if( busY==C ) $display( "    .... passed." );
        else begin 
            err_count = err_count+1;
            $display( "    .... failed, design(%b) != expected(%b)", busY, C );
        end
        $display( "Calculation restuls: %2d * %2d = %4d", A, B, busY );
        #(`HCYCLE)
        
        
        // show total results
        if( err_count==0 ) begin
            $display("****************************        /|__/|");
            $display("**                        **      / O,O  |");
            $display("**   Congratulations !!   **    /_____   |");
            $display("** All Patterns Passed!!  **   /^ ^ ^ \\  |");
            $display("**                        **  |^ ^ ^ ^ |w|");
            $display("****************************   \\m___m__|_|");
        end
        else begin
            $display("**************************** ");
            $display("           Failed ...        ");
            $display("     Total %2d Errors ...     ", err_count );
            $display("**************************** ");
        end
        
        // finish tb
        #(`CYCLE) $finish;
    end
endmodule

DSD_HW1/3-SimpleCalculator/simple_calculator.vcd
$date
	Thu Mar 21 20:44:12 2024
$end
$version
	Icarus Verilog
$end
$timescale
	10ps
$end
$scope module simple_calculator_tb $end
$var wire 8 ! busY [7:0] $end
$var wire 1 " Carry $end
$var parameter 8 # A $end
$var parameter 8 $ B $end
$var parameter 16 % C $end
$var parameter 8 & maskB0 $end
$var parameter 8 ' maskB1 $end
$var parameter 8 ( maskB2 $end
$var parameter 8 ) maskB3 $end
$var parameter 9 * sum0 $end
$var parameter 10 + sum1 $end
$var parameter 11 , sum2 $end
$var reg 1 - Clk $end
$var reg 4 . Ctrl [3:0] $end
$var reg 8 / DataIn [7:0] $end
$var reg 3 0 RW [2:0] $end
$var reg 3 1 RX [2:0] $end
$var reg 3 2 RY [2:0] $end
$var reg 1 3 Sel $end
$var reg 1 4 WEN $end
$var integer 32 5 err_count [31:0] $end
$scope module u_calc $end
$var wire 1 " Carry $end
$var wire 1 - Clk $end
$var wire 4 6 Ctrl [3:0] $end
$var wire 8 7 DataIn [7:0] $end
$var wire 3 8 RW [2:0] $end
$var wire 3 9 RX [2:0] $end
$var wire 3 : RY [2:0] $end
$var wire 1 3 Sel $end
$var wire 1 4 WEN $end
$var wire 8 ; busY [7:0] $end
$var reg 8 < X [7:0] $end
$var reg 8 = Y [7:0] $end
$var reg 1 > carry $end
$var reg 8 ? invert [7:0] $end
$var reg 8 @ r0_r [7:0] $end
$var reg 8 A r0_w [7:0] $end
$var reg 8 B r1_r [7:0] $end
$var reg 8 C r1_w [7:0] $end
$var reg 8 D r2_r [7:0] $end
$var reg 8 E r2_w [7:0] $end
$var reg 8 F r3_r [7:0] $end
$var reg 8 G r3_w [7:0] $end
$var reg 8 H r4_r [7:0] $end
$var reg 8 I r4_w [7:0] $end
$var reg 8 J r5_r [7:0] $end
$var reg 8 K r5_w [7:0] $end
$var reg 8 L r6_r [7:0] $end
$var reg 8 M r6_w [7:0] $end
$var reg 8 N r7_r [7:0] $end
$var reg 8 O r7_w [7:0] $end
$upscope $end
$upscope $end
$enddefinitions $end
$comment Show the parameter values. $end
$dumpall
b110100 ,
b0 +
b0 *
b11111111 )
b11111111 (
b0 '
b0 &
b10011100 %
b1100 $
b1101 #
$end
#0
$dumpvars
b0 O
b0 N
b0 M
b0 L
b0 K
b0 J
b0 I
b0 H
b0 G
b0 F
b0 E
b0 D
b0 C
b0 B
b0 A
b0 @
bx ?
x>
bx =
bx <
bx ;
bx :
bx 9
bx 8
bx 7
bx 6
b0 5
x4
x3
bx 2
bx 1
bx 0
bx /
bx .
1-
x"
bx !
$end
#200
0"
0>
b1101 ?
b1101 <
b0 !
b0 ;
b0 =
b1101 /
b1101 7
03
b0 .
b0 6
b0 2
b0 :
b0 1
b0 9
b1 0
b1 8
14
#500
0-
#1000
b1101 C
b1101 B
1-
#1200
b0 <
b1101 !
b1101 ;
b1101 =
b0 /
b0 7
b11 .
b11 6
b1 2
b1 :
04
#1500
0-
#2000
1-
#2200
b1100 ?
b1100 <
b0 !
b0 ;
b0 =
b1100 /
b1100 7
b0 .
b0 6
b0 2
b0 :
b10 0
b10 8
14
#2500
0-
#3000
b1100 E
b1100 D
1-
#3200
b0 <
b1100 !
b1100 ;
b1100 =
b0 /
b0 7
b11 .
b11 6
b10 2
b10 :
b1 0
b1 8
04
#3500
0-
#4000
1-
#4200
b1 <
b0 ?
b1 /
b1 7
b10 .
b10 6
b11 0
b11 8
14
#4500
0-
#5000
1-
#5200
b0 <
b0 !
b0 ;
b0 =
b0 /
b0 7
13
b1 .
b1 6
b11 2
b11 :
#5500
0-
#6000
1-
#6200
b11 .
b11 6
04
#6500
0-
#7000
1-
#7200
b110 ?
b1100 <
b1100 !
b1100 ;
b1100 =
b1001 .
b1001 6
b10 2
b10 :
b10 1
b10 9
b10 0
b10 8
14
#7500
0-
#8000
b11 ?
b110 <
b110 !
b110 ;
b110 =
b110 E
b110 D
1-
#8200
b0 ?
b1 <
b1 /
b1 7
03
b10 .
b10 6
b0 1
b0 9
b100 0
b100 8
#8500
0-
#9000
1-
#9200
b0 <
b0 !
b0 ;
b0 =
b0 /
b0 7
13
b1 .
b1 6
b100 2
b100 :
#9500
0-
#10000
1-
#10200
b11 .
b11 6
04
#10500
0-
#11000
1-
#11200
b11 ?
b110 <
b110 !
b110 ;
b110 =
b1001 .
b1001 6
b10 2
b10 :
b10 1
b10 9
b10 0
b10 8
14
#11500
0-
#12000
b1 ?
b11 <
b11 !
b11 ;
b11 =
b11 E
b11 D
1-
#12200
b1 <
b1 /
b1 7
03
b10 .
b10 6
b0 1
b0 9
b101 0
b101 8
#12500
0-
#13000
b1 K
b1 J
1-
#13200
1"
1>
b11111111 ?
b0 <
b1 !
b1 ;
b1 =
b0 /
b0 7
13
b1 .
b1 6
b101 2
b101 :
#13500
0-
#14000
0"
0>
b1 ?
b11111111 !
b11111111 ;
b11111111 =
b11111111 K
b11111111 J
1-
#14200
b11111111 ?
b11 .
b11 6
04
#14500
0-
#15000
1-
#15200
b1 ?
b11 <
b11 !
b11 ;
b11 =
b1001 .
b1001 6
b10 2
b10 :
b10 1
b10 9
b10 0
b10 8
14
#15500
0-
#16000
b0 ?
b1 <
b1 !
b1 ;
b1 =
b1 E
b1 D
1-
#16200
b1 ?
b1 /
b1 7
03
b10 .
b10 6
b0 1
b0 9
b110 0
b110 8
#16500
0-
#17000
b1 M
b1 L
1-
#17200
1"
1>
b11111111 ?
b0 <
b0 /
b0 7
13
b1 .
b1 6
b110 2
b110 :
#17500
0-
#18000
0"
0>
b1 ?
b11111111 !
b11111111 ;
b11111111 =
b11111111 M
b11111111 L
1-
#18200
b11111111 ?
b11 .
b11 6
04
#18500
0-
#19000
1-
#19200
b0 ?
b1101 <
b0 !
b0 ;
b0 =
b10 .
b10 6
b11 2
b11 :
b1 1
b1 9
b11 0
b11 8
14
#19500
0-
#20000
1-
#20200
b0 <
b0 .
b0 6
b0 1
b0 9
b111 0
b111 8
#20500
0-
#21000
1-
#21200
b11 .
b11 6
b111 2
b111 :
04
#21500
0-
#22000
1-
#22200
b1101 <
b10 .
b10 6
b100 2
b100 :
b1 1
b1 9
b100 0
b100 8
14
#22500
0-
#23000
1-
#23200
b1 <
b1 /
b1 7
03
b111 .
b111 6
b0 1
b0 9
#23500
0-
#24000
1-
#24200
b0 <
b0 /
b0 7
13
b0 .
b0 6
b111 1
b111 9
b111 0
b111 8
#24500
0-
#25000
1-
#25200
b11 .
b11 6
b111 2
b111 :
b0 1
b0 9
04
#25500
0-
#26000
1-
#26200
b1101 ?
b1101 <
b11111111 !
b11111111 ;
b11111111 =
b10 .
b10 6
b101 2
b101 :
b1 1
b1 9
b101 0
b101 8
14
#26500
0-
#27000
b1101 !
b1101 ;
b1101 =
b1101 K
b1101 J
1-
#27200
b110100 ?
b10 <
b10 /
b10 7
03
b111 .
b111 6
b0 1
b0 9
#27500
0-
#28000
b11010000 ?
b110100 !
b110100 ;
b110100 =
b110100 K
b110100 J
1-
#28200
b110100 ?
b0 <
b0 /
b0 7
13
b0 .
b0 6
b111 1
b111 9
b111 0
b111 8
#28500
0-
#29000
b1101000 ?
b110100 <
b110100 O
b110100 N
1-
#29200
b110100 ?
b0 <
b11 .
b11 6
b111 2
b111 :
b0 1
b0 9
04
#29500
0-
#30000
1-
#30200
b1101 ?
b1101 <
b11111111 !
b11111111 ;
b11111111 =
b10 .
b10 6
b110 2
b110 :
b1 1
b1 9
b110 0
b110 8
14
#30500
0-
#31000
b1101 !
b1101 ;
b1101 =
b1101 M
b1101 L
1-
#31200
b1101000 ?
b11 <
b11 /
b11 7
03
b111 .
b111 6
b0 1
b0 9
#31500
0-
#32000
1"
1>
b1000000 ?
b1101000 !
b1101000 ;
b1101000 =
b1101000 M
b1101000 L
1-
#32200
0"
0>
b10011100 ?
b110100 <
b0 /
b0 7
13
b0 .
b0 6
b111 1
b111 9
b111 0
b111 8
#32500
0-
#33000
1"
1>
b100 ?
b10011100 <
b10011100 O
b10011100 N
1-
#33200
0"
0>
b10011100 ?
b0 <
b10011100 !
b10011100 ;
b10011100 =
b11 .
b11 6
b111 2
b111 :
b0 1
b0 9
04
